<?xml version = '1.0' encoding = 'UTF-8'?>
<FKIndexAssociation class="oracle.dbtools.crest.model.design.relational.FKIndexAssociation" directorySegmentName="seg_0" id="5D547A46-2A21-6AA7-523B-BBFA62ED9082" containerWithKeyObject="8593670F-F5CC-83E6-F3A5-435A228AD8BA" localFKIndex="711483DD-DC51-D60E-07FD-9BB81BB83411" name="habitacion_inspecciones_FK">
<sourceConnName>portafolio</sourceConnName>
<sourceObjSchema>PORTAFOLIO</sourceObjSchema>
<sourceObjName>habitacion_inspecciones_FK</sourceObjName>
<createdBy>carlos</createdBy>
<createdTime>2015-10-25 00:50:26 UTC</createdTime>
<generatorID>Generado por el Usuario</generatorID>
<ownerDesignName>datamodeler</ownerDesignName>
<deleteRule>NO ACTION</deleteRule>
<referredTableID>26A54C99-CFC4-EA92-FFCF-35F49EECF151</referredTableID>
<keyObject>698B57ED-40D5-F15C-CD47-8FE90606DF78</keyObject>
<referredKeyID>698B57ED-40D5-F15C-CD47-8FE90606DF78</referredKeyID>
<mandatory>true</mandatory>
<transferable>true</transferable>
<rely>false</rely>
<columnDependencyConstraintGenerateInDDL>true</columnDependencyConstraintGenerateInDDL>
</FKIndexAssociation>